BoschMiniRpa/__init__.py
BoschMiniRpa/mini_rpa_core.py
BoschMiniRpa/mini_rpa_database_functions.py
BoschMiniRpa/mini_rpa_functions.py
BoschMiniRpa/mini_rpa_hrs_customized_functions.py
BoschMiniRpa/mini_rpa_manager.py
BoschMiniRpa/mini_rpa_sap_automation.py
BoschMiniRpa/start_rpa.py
boschminirpa-0.1.178.dist-info/licenses/LICENSE
boschminirpa-0.1.178.dist-info/METADATA
boschminirpa-0.1.178.dist-info/WHEEL
boschminirpa-0.1.178.dist-info/top_level.txt
boschminirpa-0.1.178.dist-info/RECORD
